Metadata-Version: 2.1
Name: skibiditoilet230
Version: 0.0
Summary: skibiditoilet230
Author-email: applepro285@gmail.com
